{
  "version": "2.0.0",
  "scrollSpeed": {
    "default": 2.45,
    "normal": 2.45
  },
  "events": [  ],
  "notes": {
    "normal": [
      {
        "t": 1500,
        "d": 0,
        "l": 0,
        "p": [        ]
      },
      {
        "t": 1875,
        "d": 2,
        "l": 0,
        "p": [        ]
      },
      {
        "t": 2062.5,
        "d": 0,
        "l": 0,
        "p": [        ]
      },
      {
        "t": 2156.25,
        "d": 3,
        "l": 0,
        "p": [        ]
      },
      {
        "t": 2250,
        "d": 0,
        "l": 0,
        "p": [        ]
      },
      {
        "t": 2437.5,
        "d": 1,
        "l": 0,
        "p": [        ]
      },
      {
        "t": 2625,
        "d": 2,
        "l": 0,
        "p": [        ]
      },
      {
        "t": 3000,
        "d": 3,
        "l": 0,
        "p": [        ]
      },
      {
        "t": 3187.5,
        "d": 0,
        "l": 0,
        "p": [        ]
      },
      {
        "t": 3375,
        "d": 2,
        "l": 0,
        "p": [        ]
      },
      {
        "t": 3750,
        "d": 1,
        "l": 0,
        "p": [        ]
      },
      {
        "t": 4125,
        "d": 3,
        "l": 0,
        "p": [        ]
      },
      {
        "t": 4500,
        "d": 0,
        "l": 0,
        "p": [        ]
      },
      {
        "t": 4875,
        "d": 3,
        "l": 0,
        "p": [        ]
      },
      {
        "t": 5062.5,
        "d": 0,
        "l": 0,
        "p": [        ]
      },
      {
        "t": 5156.25,
        "d": 1,
        "l": 0,
        "p": [        ]
      },
      {
        "t": 5250,
        "d": 2,
        "l": 0,
        "p": [        ]
      },
      {
        "t": 5437.5,
        "d": 1,
        "l": 0,
        "p": [        ]
      },
      {
        "t": 5625,
        "d": 0,
        "l": 0,
        "p": [        ]
      },
      {
        "t": 6000,
        "d": 0,
        "l": 0,
        "p": [        ]
      },
      {
        "t": 6187.5,
        "d": 2,
        "l": 0,
        "p": [        ]
      },
      {
        "t": 6375,
        "d": 0,
        "l": 0,
        "p": [        ]
      },
      {
        "t": 6750,
        "d": 3,
        "l": 0,
        "p": [        ]
      },
      {
        "t": 7125,
        "d": 1,
        "l": 0,
        "p": [        ]
      },
      {
        "t": 7500,
        "d": 2,
        "l": 0,
        "p": [        ]
      },
      {
        "t": 7875,
        "d": 0,
        "l": 0,
        "p": [        ]
      },
      {
        "t": 8062.5,
        "d": 2,
        "l": 0,
        "p": [        ]
      },
      {
        "t": 8156.25,
        "d": 1,
        "l": 0,
        "p": [        ]
      },
      {
        "t": 8250,
        "d": 3,
        "l": 0,
        "p": [        ]
      },
      {
        "t": 8437.5,
        "d": 0,
        "l": 0,
        "p": [        ]
      },
      {
        "t": 8625,
        "d": 1,
        "l": 0,
        "p": [        ]
      },
      {
        "t": 9000,
        "d": 2,
        "l": 0,
        "p": [        ]
      },
      {
        "t": 9187.5,
        "d": 3,
        "l": 0,
        "p": [        ]
      },
      {
        "t": 9375,
        "d": 2,
        "l": 0,
        "p": [        ]
      },
      {
        "t": 9750,
        "d": 1,
        "l": 0,
        "p": [        ]
      },
      {
        "t": 10125,
        "d": 0,
        "l": 0,
        "p": [        ]
      },
      {
        "t": 10500,
        "d": 3,
        "l": 0,
        "p": [        ]
      },
      {
        "t": 10875,
        "d": 0,
        "l": 0,
        "p": [        ]
      },
      {
        "t": 11062.5,
        "d": 2,
        "l": 0,
        "p": [        ]
      },
      {
        "t": 11156.25,
        "d": 1,
        "l": 0,
        "p": [        ]
      },
      {
        "t": 11250,
        "d": 3,
        "l": 0,
        "p": [        ]
      },
      {
        "t": 11437.5,
        "d": 0,
        "l": 0,
        "p": [        ]
      },
      {
        "t": 11625,
        "d": 3,
        "l": 0,
        "p": [        ]
      },
      {
        "t": 12000,
        "d": 1,
        "l": 0,
        "p": [        ]
      },
      {
        "t": 12187.5,
        "d": 2,
        "l": 0,
        "p": [        ]
      },
      {
        "t": 12375,
        "d": 1,
        "l": 0,
        "p": [        ]
      },
      {
        "t": 12750,
        "d": 2,
        "l": 0,
        "p": [        ]
      },
      {
        "t": 13125,
        "d": 0,
        "l": 0,
        "p": [        ]
      },
      {
        "t": 13500,
        "d": 3,
        "l": 0,
        "p": [        ]
      },
      {
        "t": 13875,
        "d": 2,
        "l": 0,
        "p": [        ]
      },
      {
        "t": 14062.5,
        "d": 3,
        "l": 0,
        "p": [        ]
      },
      {
        "t": 14156.25,
        "d": 0,
        "l": 0,
        "p": [        ]
      },
      {
        "t": 14250,
        "d": 3,
        "l": 0,
        "p": [        ]
      },
      {
        "t": 14437.5,
        "d": 1,
        "l": 0,
        "p": [        ]
      },
      {
        "t": 14625,
        "d": 2,
        "l": 0,
        "p": [        ]
      },
      {
        "t": 15000,
        "d": 0,
        "l": 0,
        "p": [        ]
      },
      {
        "t": 15187.5,
        "d": 3,
        "l": 0,
        "p": [        ]
      },
      {
        "t": 15375,
        "d": 1,
        "l": 0,
        "p": [        ]
      },
      {
        "t": 15750,
        "d": 1,
        "l": 0,
        "p": [        ]
      },
      {
        "t": 16125,
        "d": 3,
        "l": 0,
        "p": [        ]
      },
      {
        "t": 16500,
        "d": 0,
        "l": 0,
        "p": [        ]
      },
      {
        "t": 16875,
        "d": 3,
        "l": 0,
        "p": [        ]
      },
      {
        "t": 17062.5,
        "d": 0,
        "l": 0,
        "p": [        ]
      },
      {
        "t": 17156.25,
        "d": 1,
        "l": 0,
        "p": [        ]
      },
      {
        "t": 17250,
        "d": 2,
        "l": 0,
        "p": [        ]
      },
      {
        "t": 17437.5,
        "d": 1,
        "l": 0,
        "p": [        ]
      },
      {
        "t": 17625,
        "d": 0,
        "l": 0,
        "p": [        ]
      },
      {
        "t": 18000,
        "d": 3,
        "l": 0,
        "p": [        ]
      },
      {
        "t": 18187.5,
        "d": 2,
        "l": 0,
        "p": [        ]
      },
      {
        "t": 18375,
        "d": 1,
        "l": 0,
        "p": [        ]
      },
      {
        "t": 18750,
        "d": 0,
        "l": 0,
        "p": [        ]
      },
      {
        "t": 19125,
        "d": 2,
        "l": 0,
        "p": [        ]
      },
      {
        "t": 19500,
        "d": 2,
        "l": 0,
        "p": [        ]
      },
      {
        "t": 19875,
        "d": 0,
        "l": 0,
        "p": [        ]
      },
      {
        "t": 20062.5,
        "d": 2,
        "l": 0,
        "p": [        ]
      },
      {
        "t": 20156.25,
        "d": 1,
        "l": 0,
        "p": [        ]
      },
      {
        "t": 20250,
        "d": 3,
        "l": 0,
        "p": [        ]
      },
      {
        "t": 20437.5,
        "d": 0,
        "l": 0,
        "p": [        ]
      },
      {
        "t": 20625,
        "d": 1,
        "l": 0,
        "p": [        ]
      },
      {
        "t": 21000,
        "d": 2,
        "l": 0,
        "p": [        ]
      },
      {
        "t": 21187.5,
        "d": 3,
        "l": 0,
        "p": [        ]
      },
      {
        "t": 21375,
        "d": 2,
        "l": 0,
        "p": [        ]
      },
      {
        "t": 21750,
        "d": 1,
        "l": 0,
        "p": [        ]
      },
      {
        "t": 22125,
        "d": 0,
        "l": 0,
        "p": [        ]
      },
      {
        "t": 22500,
        "d": 3,
        "l": 0,
        "p": [        ]
      },
      {
        "t": 22875,
        "d": 0,
        "l": 0,
        "p": [        ]
      },
      {
        "t": 23062.5,
        "d": 2,
        "l": 0,
        "p": [        ]
      },
      {
        "t": 23156.25,
        "d": 1,
        "l": 0,
        "p": [        ]
      },
      {
        "t": 23250,
        "d": 3,
        "l": 0,
        "p": [        ]
      },
      {
        "t": 23437.5,
        "d": 0,
        "l": 0,
        "p": [        ]
      },
      {
        "t": 23625,
        "d": 3,
        "l": 0,
        "p": [        ]
      },
      {
        "t": 24000,
        "d": 1,
        "l": 0,
        "p": [        ]
      },
      {
        "t": 24187.5,
        "d": 2,
        "l": 0,
        "p": [        ]
      },
      {
        "t": 24375,
        "d": 1,
        "l": 0,
        "p": [        ]
      },
      {
        "t": 24750,
        "d": 2,
        "l": 0,
        "p": [        ]
      },
      {
        "t": 25125,
        "d": 1,
        "l": 0,
        "p": [        ]
      },
      {
        "t": 25500,
        "d": 3,
        "l": 0,
        "p": [        ]
      },
      {
        "t": 26625,
        "d": 0,
        "l": 0,
        "p": [        ]
      },
      {
        "t": 27000,
        "d": 1,
        "l": 0,
        "p": [        ]
      },
      {
        "t": 28312.5,
        "d": 2,
        "l": 0,
        "p": [        ]
      },
      {
        "t": 28406.25,
        "d": 3,
        "l": 0,
        "p": [        ]
      },
      {
        "t": 28500,
        "d": 2,
        "l": 0,
        "p": [        ]
      },
      {
        "t": 28593.75,
        "d": 1,
        "l": 0,
        "p": [        ]
      },
      {
        "t": 28687.5,
        "d": 0,
        "l": 0,
        "p": [        ]
      },
      {
        "t": 29062.5,
        "d": 0,
        "l": 0,
        "p": [        ]
      },
      {
        "t": 29250,
        "d": 1,
        "l": 0,
        "p": [        ]
      },
      {
        "t": 29625,
        "d": 2,
        "l": 0,
        "p": [        ]
      },
      {
        "t": 30000,
        "d": 3,
        "l": 0,
        "p": [        ]
      },
      {
        "t": 30562.5,
        "d": 3,
        "l": 0,
        "p": [        ]
      },
      {
        "t": 31125,
        "d": 3,
        "l": 0,
        "p": [        ]
      },
      {
        "t": 31500,
        "d": 0,
        "l": 0,
        "p": [        ]
      },
      {
        "t": 31875,
        "d": 2,
        "l": 0,
        "p": [        ]
      },
      {
        "t": 33000,
        "d": 1,
        "l": 0,
        "p": [        ]
      },
      {
        "t": 33375,
        "d": 3,
        "l": 0,
        "p": [        ]
      },
      {
        "t": 35437.5,
        "d": 1,
        "l": 0,
        "p": [        ]
      },
      {
        "t": 35531.25,
        "d": 2,
        "l": 0,
        "p": [        ]
      },
      {
        "t": 35625,
        "d": 0,
        "l": 0,
        "p": [        ]
      },
      {
        "t": 35718.75,
        "d": 3,
        "l": 0,
        "p": [        ]
      },
      {
        "t": 35812.5,
        "d": 0,
        "l": 0,
        "p": [        ]
      },
      {
        "t": 36000,
        "d": 1,
        "l": 0,
        "p": [        ]
      },
      {
        "t": 36375,
        "d": 1,
        "l": 0,
        "p": [        ]
      },
      {
        "t": 36562.5,
        "d": 2,
        "l": 0,
        "p": [        ]
      },
      {
        "t": 36937.5,
        "d": 1,
        "l": 0,
        "p": [        ]
      },
      {
        "t": 37125,
        "d": 3,
        "l": 0,
        "p": [        ]
      },
      {
        "t": 37500,
        "d": 1,
        "l": 0,
        "p": [        ]
      },
      {
        "t": 38625,
        "d": 0,
        "l": 0,
        "p": [        ]
      },
      {
        "t": 38812.5,
        "d": 3,
        "l": 0,
        "p": [        ]
      },
      {
        "t": 39000,
        "d": 1,
        "l": 0,
        "p": [        ]
      },
      {
        "t": 40312.5,
        "d": 2,
        "l": 0,
        "p": [        ]
      },
      {
        "t": 40406.25,
        "d": 1,
        "l": 0,
        "p": [        ]
      },
      {
        "t": 40500,
        "d": 3,
        "l": 0,
        "p": [        ]
      },
      {
        "t": 40593.75,
        "d": 0,
        "l": 0,
        "p": [        ]
      },
      {
        "t": 40687.5,
        "d": 3,
        "l": 0,
        "p": [        ]
      },
      {
        "t": 41062.5,
        "d": 1,
        "l": 0,
        "p": [        ]
      },
      {
        "t": 41250,
        "d": 2,
        "l": 0,
        "p": [        ]
      },
      {
        "t": 41625,
        "d": 0,
        "l": 0,
        "p": [        ]
      },
      {
        "t": 42000,
        "d": 1,
        "l": 0,
        "p": [        ]
      },
      {
        "t": 42562.5,
        "d": 1,
        "l": 0,
        "p": [        ]
      },
      {
        "t": 43125,
        "d": 1,
        "l": 0,
        "p": [        ]
      },
      {
        "t": 43500,
        "d": 2,
        "l": 0,
        "p": [        ]
      },
      {
        "t": 43875,
        "d": 1,
        "l": 0,
        "p": [        ]
      },
      {
        "t": 45000,
        "d": 0,
        "l": 0,
        "p": [        ]
      },
      {
        "t": 45375,
        "d": 3,
        "l": 0,
        "p": [        ]
      },
      {
        "t": 45937.5,
        "d": 3,
        "l": 0,
        "p": [        ]
      },
      {
        "t": 46500,
        "d": 0,
        "l": 0,
        "p": [        ]
      },
      {
        "t": 46500,
        "d": 2,
        "l": 0,
        "p": [        ]
      },
      {
        "t": 46875,
        "d": 2,
        "l": 0,
        "p": [        ]
      },
      {
        "t": 47250,
        "d": 1,
        "l": 0,
        "p": [        ]
      },
      {
        "t": 47437.5,
        "d": 3,
        "l": 0,
        "p": [        ]
      },
      {
        "t": 47531.25,
        "d": 2,
        "l": 0,
        "p": [        ]
      },
      {
        "t": 47625,
        "d": 1,
        "l": 0,
        "p": [        ]
      },
      {
        "t": 47718.75,
        "d": 0,
        "l": 0,
        "p": [        ]
      },
      {
        "t": 47812.5,
        "d": 1,
        "l": 0,
        "p": [        ]
      },
      {
        "t": 48000,
        "d": 2,
        "l": 0,
        "p": [        ]
      },
      {
        "t": 48000,
        "d": 1,
        "l": 0,
        "p": [        ]
      },
      {
        "t": 48375,
        "d": 2,
        "l": 0,
        "p": [        ]
      },
      {
        "t": 48562.5,
        "d": 3,
        "l": 0,
        "p": [        ]
      },
      {
        "t": 48937.5,
        "d": 3,
        "l": 0,
        "p": [        ]
      },
      {
        "t": 49125,
        "d": 0,
        "l": 0,
        "p": [        ]
      },
      {
        "t": 49125,
        "d": 3,
        "l": 0,
        "p": [        ]
      }
    ]
  },
  "generatedBy": "Friday Night Funkin' - v0.6.4"
}